convolution/__init__.py
convolution-0.0.1b0.dist-info/METADATA
convolution-0.0.1b0.dist-info/WHEEL
convolution-0.0.1b0.dist-info/RECORD
